simplebot_cubaweather/__init__.py
simplebot_cubaweather-0.1.0.dist-info/LICENSE
simplebot_cubaweather-0.1.0.dist-info/METADATA
simplebot_cubaweather-0.1.0.dist-info/WHEEL
simplebot_cubaweather-0.1.0.dist-info/entry_points.txt
simplebot_cubaweather-0.1.0.dist-info/top_level.txt
simplebot_cubaweather-0.1.0.dist-info/RECORD
